LICENSE
MANIFEST.in
README.rst
setup.py
django_sirtrevor_file.egg-info/PKG-INFO
django_sirtrevor_file.egg-info/SOURCES.txt
django_sirtrevor_file.egg-info/dependency_links.txt
django_sirtrevor_file.egg-info/requires.txt
django_sirtrevor_file.egg-info/top_level.txt
sirtrevor_file/__init__.py
sirtrevor_file/blocks.py
sirtrevor_file/models.py
sirtrevor_file/static/sirtrevor/blocks/file.js
sirtrevor_file/templates/sirtrevor/blocks/file.html